Localization-0.1.7.data/scripts/sample.py
localization/__init__.py
localization/find_centroid.py
localization/geoInterface.py
localization/geoProject.py
localization/geometry.py
localization/methods.py
localization/shapely_2D.py
localization/shapely_earth1.py
localization/test/__init__.py
Localization-0.1.7.dist-info/LICENSE.txt
Localization-0.1.7.dist-info/METADATA
Localization-0.1.7.dist-info/WHEEL
Localization-0.1.7.dist-info/top_level.txt
Localization-0.1.7.dist-info/RECORD
