Metadata-Version: 2.1
Name: Localization
Version: 0.1.7
Summary: Multilateration and Triangulation.
Home-page: https://github.com/kamalshadi/Localization
Author: Kamal Shadi
Author-email: kamal.shadi85@gmail.com
License: LICENSE.txt
Platform: UNKNOWN
